zimran/django/__init__.py
zimran/django/middleware/__init__.py
zimran/django/middleware/http_host_rename.py
zimran_django-0.0.2.dist-info/METADATA
zimran_django-0.0.2.dist-info/WHEEL
zimran_django-0.0.2.dist-info/top_level.txt
zimran_django-0.0.2.dist-info/RECORD
