Metadata-Version: 2.1
Name: zimran-django
Version: 0.0.2
Summary: Extensions for Django services
Requires-Python: >=3.10
Requires-Dist: django
